{
  "crebo": "27004",
  "opleiding": "27004_BOL_2025__oer-2025-2026-ci-27004-signspecialist",
  "bron": "CompetentNL",
  "beroep": {
    "label": "Signspecialist",
    "uri": "",
    "definitie": "De signspecialist coördineert de ontwikkeling van signproducten zoals reclameborden, auto-, gevel- en lichtreclame. Die denkt mee tijdens het ontwerp van de producten, en tijdens de uitvoering is hij projectleider. Een belangrijke taak is het contact onderhouden met alle betrokkenen bij een project, waarbij die direct contact met de opdrachtgever heeft. De signspecialist houdt goed in de gaten of concepten ook praktisch uitvoerbaar zijn. De signspecialist heeft technische kennis van materialen en software,  werkt zelfstandig en neemt zelf beslissingen. De signspecialist draagt de verantwoordelijkheid voor een goede oplevering van het product."
  },
  "match_methode": "crebo-direct",
  "kandidaten": [],
  "skills": [
    {
      "label": "Gereedschappen en apparaten gebruiken",
      "uri": "https://linkeddata.competentnl.nl/id/humancapability/072570C444",
      "categorie": "essentieel"
    },
    {
      "label": "Samenwerken",
      "uri": "https://linkeddata.competentnl.nl/id/humancapability/1D54A21B60",
      "categorie": "essentieel"
    },
    {
      "label": "Materiaal en gereedschap uitkiezen",
      "uri": "https://linkeddata.competentnl.nl/id/humancapability/4257E202F2",
      "categorie": "essentieel"
    },
    {
      "label": "Beoordelen van functioneren en kwaliteit",
      "uri": "https://linkeddata.competentnl.nl/id/humancapability/4F97986168",
      "categorie": "essentieel"
    },
    {
      "label": "Monitoren",
      "uri": "https://linkeddata.competentnl.nl/id/humancapability/B03F4F484C",
      "categorie": "essentieel"
    },
    {
      "label": "Ontwerpen van systemen en producten",
      "uri": "https://linkeddata.competentnl.nl/id/humancapability/B4866702BB",
      "categorie": "essentieel"
    },
    {
      "label": "Administreren",
      "uri": "https://linkeddata.competentnl.nl/id/humancapability/B6D93142FE",
      "categorie": "essentieel"
    },
    {
      "label": "Financiële middelen beheren",
      "uri": "https://linkeddata.competentnl.nl/id/humancapability/BC3AB34C1A",
      "categorie": "essentieel"
    },
    {
      "label": "Leergierig zijn",
      "uri": "https://linkeddata.competentnl.nl/id/humancapability/CB768EFA19",
      "categorie": "essentieel"
    },
    {
      "label": "(digitale) Informatie beheren",
      "uri": "https://linkeddata.competentnl.nl/id/humancapability/CD7B4C0F34",
      "categorie": "essentieel"
    },
    {
      "label": "Installeren",
      "uri": "https://linkeddata.competentnl.nl/id/humancapability/D5AD4F0905",
      "categorie": "essentieel"
    },
    {
      "label": "Plannen",
      "uri": "https://linkeddata.competentnl.nl/id/humancapability/D8863A73CA",
      "categorie": "essentieel"
    },
    {
      "label": "Organiseren",
      "uri": "https://linkeddata.competentnl.nl/id/humancapability/DEDBBC55E0",
      "categorie": "essentieel"
    },
    {
      "label": "Promoten",
      "uri": "https://linkeddata.competentnl.nl/id/humancapability/E06265451B",
      "categorie": "essentieel"
    },
    {
      "label": "Productietechniek",
      "uri": "https://linkeddata.competentnl.nl/id/knowledgearea/04541FC2D1",
      "categorie": "essentieel"
    },
    {
      "label": "Bediening van bedrijfswerktuigen",
      "uri": "https://linkeddata.competentnl.nl/id/knowledgearea/2268CFE4F6",
      "categorie": "essentieel"
    },
    {
      "label": "Nederlands recht, algemeen recht, rechterlijke macht",
      "uri": "https://linkeddata.competentnl.nl/id/knowledgearea/29022BA6BC",
      "categorie": "essentieel"
    },
    {
      "label": "Grafisch ontwerpen",
      "uri": "https://linkeddata.competentnl.nl/id/knowledgearea/2DC70C1A23",
      "categorie": "essentieel"
    },
    {
      "label": "Installatietechniek (elektro)",
      "uri": "https://linkeddata.competentnl.nl/id/knowledgearea/3F26F4FE84",
      "categorie": "essentieel"
    },
    {
      "label": "Bedrijfseconomie",
      "uri": "https://linkeddata.competentnl.nl/id/knowledgearea/53B4B474D1",
      "categorie": "essentieel"
    },
    {
      "label": "Afbouw",
      "uri": "https://linkeddata.competentnl.nl/id/knowledgearea/545738E767",
      "categorie": "essentieel"
    },
    {
      "label": "Administratie",
      "uri": "https://linkeddata.competentnl.nl/id/knowledgearea/5488DA6138",
      "categorie": "essentieel"
    },
    {
      "label": "Bedrijfstechniek, (technische) bedrijfsvoering",
      "uri": "https://linkeddata.competentnl.nl/id/knowledgearea/6CAB3D969E",
      "categorie": "essentieel"
    },
    {
      "label": "Metaalkunde, metaalbewerking",
      "uri": "https://linkeddata.competentnl.nl/id/knowledgearea/800D4C8975",
      "categorie": "essentieel"
    },
    {
      "label": "Kleurenleer",
      "uri": "https://linkeddata.competentnl.nl/id/knowledgearea/814C4DE179",
      "categorie": "essentieel"
    },
    {
      "label": "Ontwerpen met de computer",
      "uri": "https://linkeddata.competentnl.nl/id/knowledgearea/8F02A2B716",
      "categorie": "essentieel"
    },
    {
      "label": "Techniek en technische dienstverlening",
      "uri": "https://linkeddata.competentnl.nl/id/knowledgearea/920C3F455D",
      "categorie": "essentieel"
    },
    {
      "label": "Informatiemanagement",
      "uri": "https://linkeddata.competentnl.nl/id/knowledgearea/9212BF2426",
      "categorie": "essentieel"
    },
    {
      "label": "Samenwerking en netwerken",
      "uri": "https://linkeddata.competentnl.nl/id/knowledgearea/95C3218741",
      "categorie": "essentieel"
    },
    {
      "label": "Installatietechniek (infra)",
      "uri": "https://linkeddata.competentnl.nl/id/knowledgearea/A767523AD9",
      "categorie": "essentieel"
    },
    {
      "label": "Arbeidsomstandigheden",
      "uri": "https://linkeddata.competentnl.nl/id/knowledgearea/BD87CBDBDC",
      "categorie": "essentieel"
    },
    {
      "label": "Veiligheidskunde",
      "uri": "https://linkeddata.competentnl.nl/id/knowledgearea/C34CD6448D",
      "categorie": "essentieel"
    },
    {
      "label": "Maten en getallen",
      "uri": "https://linkeddata.competentnl.nl/id/knowledgearea/CB6BD3297B",
      "categorie": "essentieel"
    },
    {
      "label": "Ladingbehandeling en intern transport",
      "uri": "https://linkeddata.competentnl.nl/id/knowledgearea/D27283387C",
      "categorie": "essentieel"
    },
    {
      "label": "Reclame",
      "uri": "https://linkeddata.competentnl.nl/id/knowledgearea/D423138CBB",
      "categorie": "essentieel"
    },
    {
      "label": "Marketing",
      "uri": "https://linkeddata.competentnl.nl/id/knowledgearea/E6A75FB995",
      "categorie": "essentieel"
    },
    {
      "label": "Projectmanagement",
      "uri": "https://linkeddata.competentnl.nl/id/knowledgearea/F248B939CD",
      "categorie": "essentieel"
    }
  ]
}